license.md
setup.py
PARE_TOOLBOX/PARE.py
PARE_TOOLBOX/PARE_LIBRARY.py
PARE_TOOLBOX/__init__.py
PARE_TOOLBOX.egg-info/PKG-INFO
PARE_TOOLBOX.egg-info/SOURCES.txt
PARE_TOOLBOX.egg-info/dependency_links.txt
PARE_TOOLBOX.egg-info/requires.txt
PARE_TOOLBOX.egg-info/top_level.txt