Metadata-Version: 2.1
Name: PARE-TOOLBOX
Version: 2023.8
Summary: The PAREpy is an easy-to-use environment for applying probabilistic modeling.
Home-page: https://wmpjrufg.github.io/PAREPY/
Author: ['Wanderlei Malaquias Pereira Junior', 'Donizetti Aparecido de Souza Junior', 'Romes Antônio Borges', 'Mateus Pereira da Silva']
Author-email: wanderlei_junior@ufcat.edu.br
License: MIT License
Classifier: Development Status :: 4 - Beta
Classifier: Topic :: Education
Classifier: Topic :: Scientific/Engineering
Classifier: License :: OSI Approved :: MIT License
Classifier: Programming Language :: Python
License-File: license.md
